[
    {
        "date": "2024-12-31",
        "symbol": "META",
        "reportedCurrency": "USD",
        "cik": "0001326801",
        "fillingDate": "2025-01-30",
        "acceptedDate": "2025-01-29 20:00:50",
        "calendarYear": "2024",
        "period": "FY",
        "revenue": 164501000000,
        "costOfRevenue": 30161000000,
        "grossProfit": 134340000000,
        "grossProfitRatio": 0.8166515705,
        "researchAndDevelopmentExpenses": 43873000000,
        "generalAndAdministrativeExpenses": 9740000000,
        "sellingAndMarketingExpenses": 11347000000,
        "sellingGeneralAndAdministrativeExpenses": 21087000000,
        "otherExpenses": 0,
        "operatingExpenses": 64960000000,
        "costAndExpenses": 95121000000,
        "interestIncome": 2517000000,
        "interestExpense": 715000000,
        "depreciationAndAmortization": 15498000000,
        "ebitda": 86876000000,
        "ebitdaratio": 0.5281183701,
        "operatingIncome": 69380000000,
        "operatingIncomeRatio": 0.421760354,
        "totalOtherIncomeExpensesNet": 1283000000,
        "incomeBeforeTax": 70663000000,
        "incomeBeforeTaxRatio": 0.4295596987,
        "incomeTaxExpense": 8303000000,
        "netIncome": 62360000000,
        "netIncomeRatio": 0.3790858414,
        "eps": 24.61,
        "epsdiluted": 23.86,
        "weightedAverageShsOut": 2534000000,
        "weightedAverageShsOutDil": 2614000000,
        "link": "https://www.sec.gov/Archives/edgar/data/1326801/000132680125000017/0001326801-25-000017-index.htm",
        "finalLink": "https://www.sec.gov/Archives/edgar/data/1326801/000132680125000017/meta-20241231.htm"
    }
]